hanoi_python_solver/__init__.py
hanoi_python_solver/abc_notation.py
hanoi_python_solver/abc_notation.pyi
hanoi_python_solver/hanoi.py
hanoi_python_solver/hanoi.pyi
hanoi_python_solver/network.py
hanoi_python_solver/network.pyi
hanoi_python_solver/node.py
hanoi_python_solver/node.pyi
hanoi_python_solver/poteau.py
hanoi_python_solver/poteau.pyi
hanoi_python_solver-1.1.0.dist-info/LICENSE
hanoi_python_solver-1.1.0.dist-info/METADATA
hanoi_python_solver-1.1.0.dist-info/WHEEL
hanoi_python_solver-1.1.0.dist-info/top_level.txt
hanoi_python_solver-1.1.0.dist-info/RECORD
