Metadata-Version: 2.1
Name: hanoi_python_solver
Version: 1.1.0
Summary: implementation of Tower of Hanoi game + shortest path to resolution at each step
Home-page: https://github.com/esHome33/hanoi_python_solver/
Author: ESHome33
Author-email: eshome.fr@gmail.com
License: MIT
License-File: LICENSE
